popmodel/__init__.py
popmodel/absprofile.py
popmodel/atmcalcs.py
popmodel/command_line.py
popmodel/loadhitran.py
popmodel/main.py
popmodel/ohcalcs.py
popmodel/simspec.py
popmodel/sweep.py
popmodel/version.py
popmodel/data/hitran_sample.par
popmodel/data/parameters_template.yaml
popmodel-0.4.0.dist-info/DESCRIPTION.rst
popmodel-0.4.0.dist-info/METADATA
popmodel-0.4.0.dist-info/RECORD
popmodel-0.4.0.dist-info/WHEEL
popmodel-0.4.0.dist-info/entry_points.txt
popmodel-0.4.0.dist-info/metadata.json
popmodel-0.4.0.dist-info/top_level.txt
