Metadata-Version: 2.0
Name: popmodel
Version: 0.4.0
Summary: Model molecular excited state populations over time
Home-page: https://github.com/awbirdsall/popmodel
Author: Adam Birdsall
Author-email: abirdsall@gmail.com
License: MIT
Keywords: spectroscopy,fluorescence,model,chemistry,atmosphere
Platform: UNKNOWN
Classifier: Development Status :: 3 - Alpha
Classifier: Intended Audience :: Science/Research
Classifier: Topic :: Scientific/Engineering :: Atmospheric Science
Classifier: Topic :: Scientific/Engineering :: Chemistry
Classifier: Topic :: Scientific/Engineering :: Physics
Classifier: License :: OSI Approved :: MIT License
Classifier: Programming Language :: Python :: 2
Classifier: Programming Language :: Python :: 2.7
Classifier: Programming Language :: Python :: 3
Classifier: Programming Language :: Python :: 3.5
Requires-Dist: matplotlib (>=1.5)
Requires-Dist: numpy
Requires-Dist: pandas
Requires-Dist: pyyaml
Requires-Dist: scipy
